hdl/encoder_8to3.v
module encoder_8to3(
    input [7:0] data,
    output reg [2:0] code
);

always @ (data)
begin
    case(data)

    8'h01 : code = 3'b000;
    8'h02 : code = 3'b001;
    8'h04 : code = 3'b010;
    8'h08 : code = 3'b011;
    8'h10 : code = 3'b100;
    8'h20 : code = 3'b101;
    8'h40 : code = 3'b110;
    8'h80 : code = 3'b111;
    default: code = 3'bx;

    endcase
end

endmodule

test/tb_encoder_8to3.v
module tb_encoder_8to3();

    reg [7:0] data;
    wire [2:0] code;
    
    encoder_8to3 uut(
        .data(data),
        .code(code)
    );

    initial begin
        $dumpfile("simulation/tb_encoder_8to3.vcd");
        $dumpvars(0, tb_encoder_8to3);

        data = 8'h01;
        #2 data = 8'h02;
        #4 data = 8'h04;
        #6 data = 8'h08;
        #8 data = 8'h10;
        #10 data = 8'h20;
        #12 data = 8'h40;
        #14 data = 8'h80;

        #20;
        $finish;
    end

    initial begin
        $monitor($time, "  data = %b  code = %b   |  data = %x  code = %x", data, code, data, code);
    end
    endmodule

simulation/tb_encoder_8to3.vcd
$date
	Mon Apr 19 22:11:06 2021
$end
$version
	Icarus Verilog
$end
$timescale
	1s
$end
$scope module tb_encoder_8to3 $end
$var wire 3 ! code [2:0] $end
$var reg 8 " data [7:0] $end
$scope module uut $end
$var wire 8 # data [7:0] $end
$var reg 3 $ code [2:0] $end
$upscope $end
$upscope $end
$enddefinitions $end
#0
$dumpvars
b0 $
b1 #
b1 "
b0 !
$end
#2
b1 !
b1 $
b10 "
b10 #
#6
b10 !
b10 $
b100 "
b100 #
#12
b11 !
b11 $
b1000 "
b1000 #
#20
b100 !
b100 $
b10000 "
b10000 #
#30
b101 !
b101 $
b100000 "
b100000 #
#42
b110 !
b110 $
b1000000 "
b1000000 #
#56
b111 !
b111 $
b10000000 "
b10000000 #
